[{
    "id": 1,
    "title": "Lawn & Garden",
    "thumb": "https://source.unsplash.com/1600x900/?product",
    "images": ["https://source.unsplash.com/1600x900/?product"],
    "slug": "lawn_garden",
    "description": "Your lawn and garden can do a lot for the beauty and value of your home, and gardening and lawn care can do a lot for your peace of mind, too, if you know what equipment and supplies you’ll need. Start now and get expert information on everything you need for your lawn/garden..",
    "status": "published",
    "postDate": "20-03-2019 10:10:11",
    "lastUpdated": "20-03-2019 10:10:11"

},
{
    "id": 2,
    "title": "Lawn & Garden",
    "thumb": "https://source.unsplash.com/1600x900/?product",
    "images": ["https://source.unsplash.com/1600x900/?product"],
    "slug": "lawn_garden",
    "description": "Your lawn and garden can do a lot for the beauty and value of your home, and gardening and lawn care can do a lot for your peace of mind, too, if you know what equipment and supplies you’ll need. Start now and get expert information on everything you need for your lawn/garden..",
    "status": "published",
    "postDate": "20-03-2019 10:10:11",
    "lastUpdated": "20-03-2019 10:10:11"
},
{
    "id": 3,
    "title": "Lawn & Garden",
    "thumb": "https://source.unsplash.com/1600x900/?product",
    "images": ["https://source.unsplash.com/1600x900/?product"],
    "slug": "lawn_garden",
    "description": "Your lawn and garden can do a lot for the beauty and value of your home, and gardening and lawn care can do a lot for your peace of mind, too, if you know what equipment and supplies you’ll need. Start now and get expert information on everything you need for your lawn/garden..",
    "status": "published",
    "postDate": "20-03-2019 10:10:11",
    "lastUpdated": "20-03-2019 10:10:11"
}]